{
    "type": "Program",
    "statements": [
        {
            "type": "Assignment",
            "name": "xmax",
            "value": {
                "type": "IntLiteral",
                "value": 1
            }
        },
        {
            "type": "Assignment",
            "name": "xmin",
            "value": {
                "type": "FloatLiteral",
                "value": -2.0
            }
        },
        {
            "type": "Assignment",
            "name": "ymin",
            "value": {
                "type": "FloatLiteral",
                "value": -1.5
            }
        },
        {
            "type": "Assignment",
            "name": "ymax",
            "value": {
                "type": "FloatLiteral",
                "value": 1.5
            }
        },
        {
            "type": "Assignment",
            "name": "threshhold",
            "value": {
                "type": "IntLiteral",
                "value": 1000
            }
        }
    ]
}